anamnesis/__init__.py
anamnesis/abstract.py
anamnesis/mpihandler.py
anamnesis/options.py
anamnesis/register.py
anamnesis/store.py
anamnesis/mpiimps/__init__.py
anamnesis/mpiimps/mpifourpy.py
anamnesis/mpiimps/null.py
anamnesis/test/__init__.py
anamnesis/test/support.py
anamnesis/test/data/__init__.py
anamnesis/test/data/badclassname.hdf5
anamnesis/test/data/namemap_example.hdf5
anamnesis/test/data/simplestore.hdf5
anamnesis/test/data/test_newlist.hdf5
anamnesis/test/data/test_oldlist.hdf5
anamnesis/tests/__init__.py
anamnesis/tests/class_example.py
anamnesis/tests/namemap_example.py
anamnesis/tests/test_abstract.py
anamnesis/tests/test_options.py
anamnesis/tests/test_register.py
anamnesis/tests/test_store.py
anamnesis-1.0.4.dist-info/LICENSE.txt
anamnesis-1.0.4.dist-info/METADATA
anamnesis-1.0.4.dist-info/WHEEL
anamnesis-1.0.4.dist-info/top_level.txt
anamnesis-1.0.4.dist-info/RECORD
